CHANGES.txt
README.txt
setup.py
gocept/__init__.py
gocept.datetimewidget.egg-info/PKG-INFO
gocept.datetimewidget.egg-info/SOURCES.txt
gocept.datetimewidget.egg-info/dependency_links.txt
gocept.datetimewidget.egg-info/entry_points.txt
gocept.datetimewidget.egg-info/namespace_packages.txt
gocept.datetimewidget.egg-info/not-zip-safe
gocept.datetimewidget.egg-info/requires.txt
gocept.datetimewidget.egg-info/top_level.txt
gocept/datetimewidget/EXTERNALS.txt
gocept/datetimewidget/__init__.py
gocept/datetimewidget/configure.zcml
gocept/datetimewidget/interfaces.py
gocept/datetimewidget/overrides.zcml
gocept/datetimewidget/resource.py
gocept/datetimewidget/viewlet.py
gocept/datetimewidget/resources/calendar-blue.css
gocept/datetimewidget/resources/calendar-blue2.css
gocept/datetimewidget/resources/calendar-brown.css
gocept/datetimewidget/resources/calendar-green.css
gocept/datetimewidget/resources/calendar-setup.js
gocept/datetimewidget/resources/calendar-system.css
gocept/datetimewidget/resources/calendar-tas.css
gocept/datetimewidget/resources/calendar-win2k-1.css
gocept/datetimewidget/resources/calendar-win2k-2.css
gocept/datetimewidget/resources/calendar-win2k-cold-1.css
gocept/datetimewidget/resources/calendar-win2k-cold-2.css
gocept/datetimewidget/resources/calendar.js
gocept/datetimewidget/resources/datetimewidget.js
gocept/datetimewidget/resources/fix_up_css.sh
gocept/datetimewidget/resources/img.gif
gocept/datetimewidget/resources/menuarrow.gif
gocept/datetimewidget/resources/menuarrow2.gif
gocept/datetimewidget/resources/languages/calendar-al.js
gocept/datetimewidget/resources/languages/calendar-bg.js
gocept/datetimewidget/resources/languages/calendar-big5.js
gocept/datetimewidget/resources/languages/calendar-br.js
gocept/datetimewidget/resources/languages/calendar-ca.js
gocept/datetimewidget/resources/languages/calendar-cs-win.js
gocept/datetimewidget/resources/languages/calendar-da.js
gocept/datetimewidget/resources/languages/calendar-de.js
gocept/datetimewidget/resources/languages/calendar-en.js
gocept/datetimewidget/resources/languages/calendar-es.js
gocept/datetimewidget/resources/languages/calendar-fr.js
gocept/datetimewidget/resources/languages/calendar-hu.js
gocept/datetimewidget/resources/languages/calendar-it.js
gocept/datetimewidget/resources/languages/calendar-ja.js
