Metadata-Version: 1.0
Name: gocept.datetimewidget
Version: 1.2
Summary: Integration package for using zc.datetimewidget in Zope 2
Home-page: UNKNOWN
Author: Daniel Havlik
Author-email: dh@gocept.com
License: ZPL
Keywords: date datetime widget zope2 zope3 zope.formlib
Platform: UNKNOWN
Classifier: Programming Language :: Python
Classifier: Development Status :: 5 - Production/Stable
Classifier: Environment :: Web Environment
Classifier: Intended Audience :: Developers
Classifier: License :: OSI Approved :: Zope Public License
Classifier: Programming Language :: Python
Classifier: Natural Language :: English
Classifier: Operating System :: OS Independent
Classifier: Topic :: Internet :: WWW/HTTP
Classifier: Framework :: Zope2
